AUTHORS
LICENSE
MANIFEST.in
README.rst
setup.py
django_formadmin.egg-info/PKG-INFO
django_formadmin.egg-info/SOURCES.txt
django_formadmin.egg-info/dependency_links.txt
django_formadmin.egg-info/not-zip-safe
django_formadmin.egg-info/top_level.txt
formadmin/__init__.py
formadmin/admin.py
formadmin/hacks.py
formadmin/models.py
formadmin/settings.py
formadmin/sites.py
formadmin/views.py